LICENSE
README.md
pyproject.toml
setup.py
pyclimo/__init__.py
pyclimo/calc.py
pyclimo/cmaps.py
pyclimo/coords.py
pyclimo/file_funcs.py
pyclimo/geometry.py
pyclimo/noaa_psl.py
pyclimo/noaa_psl_data.py
pyclimo/prism.py
pyclimo/prism_data.py
pyclimo/time_funcs.py
pyclimo.egg-info/PKG-INFO
pyclimo.egg-info/SOURCES.txt
pyclimo.egg-info/dependency_links.txt
pyclimo.egg-info/requires.txt
pyclimo.egg-info/top_level.txt